Metadata-Version: 2.1
Name: orngpenguen
Version: 0.0.1
Summary: Password Hasher with a key
Home-page: UNKNOWN
Author: Mert Alperen Beşer
Author-email: mertbeser77@gmail.com
License: MIT
Keywords: hash
Platform: UNKNOWN
Classifier: Development Status :: 5 - Production/Stable
Classifier: Intended Audience :: Education
Classifier: Operating System :: Microsoft :: Windows :: Windows 10
Classifier: License :: OSI Approved :: MIT License
Classifier: Programming Language :: Python :: 3
License-File: LICENCE.txt
